Metadata-Version: 1.0
Name: oddsman
Version: 0.1.1
Summary: this module extracts odds(rate) of hourse race held today 
Home-page: https://github.com/PinkPhayate/OddsWatcher
Author: phayate
Author-email: pinqphayat@gmail.com
License: MIT
Keywords: hourse race odds
Platform: UNKNOWN
